{
    "name": "@ohos/libffi",
    "version": "",
    "description": "Third-party open-source software libffi | 三方开源软件libffi",
    "homePage": "https://gitee.com/openharmony",
    "license": "MIT",
    "repository": "https://gitee.com/openharmony/third_party_libffi",
    "domain": "os",
    "language": "",
    "publishAs": "code-segment",
    "private": false,
    "scripts": {},
    "tags": [
        "third_party"
    ],
    "keywords": [
        "third-party",
        "libffi"
    ],
    "envs": [],
    "dirs": [],
    "segment": {
        "destPath": "third_party/libffi"
    },
    "component": {
        "name": "thirdparty_libffi",
        "subsystem": "",
        "syscap": [],
        "features": [],
        "adapted_system_type": [],
        "rom": "",
        "ram": "",
        "build": {
            "sub_component": [],
            "inner_kits": [],
            "test": []
        }
    }
}